deepcpg/__init__.py
deepcpg/callbacks.py
deepcpg/evaluation.py
deepcpg/metrics.py
deepcpg/motifs.py
deepcpg/utils.py
deepcpg/data/__init__.py
deepcpg/data/annotations.py
deepcpg/data/dna.py
deepcpg/data/fasta.py
deepcpg/data/feature_extractor.py
deepcpg/data/hdf.py
deepcpg/data/stats.py
deepcpg/data/utils.py
deepcpg/models/__init__.py
deepcpg/models/cpg.py
deepcpg/models/dna.py
deepcpg/models/joint.py
deepcpg/models/utils.py
deepcpg-1.0.7.data/scripts/dcpg_data.py
deepcpg-1.0.7.data/scripts/dcpg_data_show.py
deepcpg-1.0.7.data/scripts/dcpg_data_stats.py
deepcpg-1.0.7.data/scripts/dcpg_download.py
deepcpg-1.0.7.data/scripts/dcpg_eval.py
deepcpg-1.0.7.data/scripts/dcpg_eval_export.py
deepcpg-1.0.7.data/scripts/dcpg_eval_perf.py
deepcpg-1.0.7.data/scripts/dcpg_filter_act.py
deepcpg-1.0.7.data/scripts/dcpg_filter_motifs.py
deepcpg-1.0.7.data/scripts/dcpg_snp.py
deepcpg-1.0.7.data/scripts/dcpg_train.py
deepcpg-1.0.7.data/scripts/dcpg_train_viz.py
deepcpg-1.0.7.dist-info/LICENSE
deepcpg-1.0.7.dist-info/METADATA
deepcpg-1.0.7.dist-info/WHEEL
deepcpg-1.0.7.dist-info/top_level.txt
deepcpg-1.0.7.dist-info/RECORD
