Metadata-Version: 2.1
Name: deepcpg
Version: 1.0.7
Summary: Deep learning for predicting CpG methylation
Home-page: https://github.com/cangermueller/deepcpg
Author: Christof Angermueller
Author-email: cangermueller@gmail.com
License: MIT
Keywords: Deep learning,Deep neural networks,Epigenetics,DNA methylation,Single cells
Platform: UNKNOWN
Classifier: Development Status :: 5 - Production/Stable
Classifier: Environment :: Console
Classifier: Intended Audience :: Science/Research
Classifier: License :: OSI Approved :: MIT License
Classifier: Natural Language :: English
Classifier: Programming Language :: Python
Classifier: Programming Language :: Python :: 2
Classifier: Programming Language :: Python :: 2.7
Classifier: Programming Language :: Python :: 3
Classifier: Programming Language :: Python :: 3.3
Classifier: Programming Language :: Python :: 3.4
Classifier: Programming Language :: Python :: 3.5
Classifier: Topic :: Scientific/Engineering :: Artificial Intelligence
Classifier: Topic :: Scientific/Engineering :: Bio-Informatics
Requires-Dist: h5py
Requires-Dist: argparse
Requires-Dist: scikit-learn
Requires-Dist: scipy
Requires-Dist: pandas
Requires-Dist: numpy
Requires-Dist: pytest
Requires-Dist: keras
Requires-Dist: matplotlib
Requires-Dist: seaborn
